[
  {
    "episode_number": "714",
    "guests": [
      "Howard Stern",
      "Stefan Molyneux",
      "Wolfgang Halbig",
      "Alex Lee Moyer",
      "James Tracy",
      "Paul Joseph Watson"
    ]
  },
  {
    "episode_number": "715",
    "guests": [
      "Mike Lindell",
      "Robert Barnes",
      "Mike Adams",
      "Glenn Beck",
      "Roger Stone",
      "Dick Cheney"
    ]
  },
  {
    "episode_number": "716",
    "guests": [
      "Glenn Beck",
      "David Knight",
      "Rush Limbaugh",
      "Charlie Sheen"
    ]
  },
  {
    "episode_number": "717",
    "guests": [
      "Aaron Russo",
      "Laura Loomer",
      "Savannah Hernandez"
    ]
  },
  {
    "episode_number": "718",
    "guests": [
      "Alexander Dugin",
      "Glenn Beck",
      "Greg Reese"
    ]
  },
  {
    "episode_number": "719",
    "guests": [
      "Brian Stelter",
      "Sam Harris",
      "Greg Reese",
      "Glenn Beck",
      "Glenn Greenwald",
      "Tucker Carlson",
      "George Washington"
    ]
  }
]